{"type":"FeatureCollection","features":[{"type":"Feature","geometry":{"type":"Point","coordinates":[-118.9732,-54.6008]},"properties":{"id":"EQ1551421","provider":"GDACS","sourceUrl":"https://www.gdacs.org/report.aspx?eventtype=EQ&eventid=1551421","category":"earthquake","event":"Green earthquake (Magnitude 5.5M, Depth:10km) in Southern East Pacific Rise 12/07/2026 07:29 UTC, [unknown].","severity":"unknown","headline":"Green earthquake (Magnitude 5.5M, Depth:10km) in Southern East Pacific Rise 12/07/2026 07:29 UTC, [unknown].","description":"On 7/12/2026 7:29:23 AM, an earthquake occurred in Southern East Pacific Rise potentially affecting [unknown]. The earthquake had Magnitude 5.5M, Depth:10km.","updated":"Sun, 12 Jul 2026 07:47:57 GMT","layer":"alerts","priority":0,"attribution":"Global Disaster Alert and Coordination System (GDACS)"}},{"type":"Feature","geometry":{"type":"Point","coordinates":[-28.8526,-55.5424]},"properties":{"id":"EQ1551279","provider":"GDACS","sourceUrl":"https://www.gdacs.org/report.aspx?eventtype=EQ&eventid=1551279","category":"earthquake","event":"Green earthquake (Magnitude 6.4M, Depth:26km) in South Sandwich Islands Region 11/07/2026 10:26 UTC, [unknown].","severity":"unknown","headline":"Green earthquake (Magnitude 6.4M, Depth:26km) in South Sandwich Islands Region 11/07/2026 10:26 UTC, [unknown].","description":"On 7/11/2026 10:26:45 AM, an earthquake occurred in South Sandwich Islands Region potentially affecting [unknown]. The earthquake had Magnitude 6.4M, Depth:26km.","updated":"Sat, 11 Jul 2026 10:45:18 GMT","layer":"alerts","priority":0,"attribution":"Global Disaster Alert and Coordination System (GDACS)"}},{"type":"Feature","geometry":{"type":"Point","coordinates":[154.8869,-61.7788]},"properties":{"id":"EQ1550840","provider":"GDACS","sourceUrl":"https://www.gdacs.org/report.aspx?eventtype=EQ&eventid=1550840","category":"earthquake","event":"Green earthquake (Magnitude 5.5M, Depth:10km) in Balleny Islands Region 08/07/2026 19:07 UTC, [unknown].","severity":"unknown","headline":"Green earthquake (Magnitude 5.5M, Depth:10km) in Balleny Islands Region 08/07/2026 19:07 UTC, [unknown].","description":"On 7/8/2026 7:07:10 PM, an earthquake occurred in Balleny Islands Region potentially affecting [unknown]. The earthquake had Magnitude 5.5M, Depth:10km.","updated":"Wed, 08 Jul 2026 19:29:02 GMT","layer":"alerts","priority":0,"attribution":"Global Disaster Alert and Coordination System (GDACS)"}},{"type":"Feature","geometry":{"type":"Point","coordinates":[168.8353,-20.2559]},"properties":{"id":"EQ1550772","provider":"GDACS","sourceUrl":"https://www.gdacs.org/report.aspx?eventtype=EQ&eventid=1550772","category":"earthquake","event":"Green earthquake (Magnitude 5.8M, Depth:10km) in Vanuatu 08/07/2026 09:50 UTC, 10 thousand in MMI IV.","severity":"unknown","headline":"Green earthquake (Magnitude 5.8M, Depth:10km) in Vanuatu 08/07/2026 09:50 UTC, 10 thousand in MMI IV.","description":"On 7/8/2026 9:50:23 AM, an earthquake occurred in Vanuatu potentially affecting 10 thousand in MMI IV. The earthquake had Magnitude 5.8M, Depth:10km.","updated":"Wed, 08 Jul 2026 10:10:52 GMT","layer":"alerts","priority":0,"attribution":"Global Disaster Alert and Coordination System (GDACS)"}},{"type":"Feature","geometry":{"type":"Point","coordinates":[-28.8526,-55.5424,26]},"properties":{"id":"us7000szpb","provider":"USGS_EARTHQUAKES","sourceUrl":"https://earthquake.usgs.gov/earthquakes/eventpage/us7000szpb","category":"earthquake","event":"Earthquake","severity":"severe","headline":"M 6.4 - South Sandwich Islands region","description":"Magnitude 6.4; place: South Sandwich Islands region","areaName":"South Sandwich Islands region","effective":"2026-07-11T10:26:42+00:00","onset":"2026-07-11T10:26:42+00:00","updated":"2026-07-11T10:26:42+00:00","layer":"earthquakes","priority":3,"attribution":"U.S. Geological Survey"}}]}